trix/__init__.py
trix/auth.py
trix/client.py
trix/exceptions.py
trix/protocols.py
trix/types.py
trix/resources/__init__.py
trix/resources/agent.py
trix/resources/base.py
trix/resources/clusters.py
trix/resources/enrichments.py
trix/resources/entities.py
trix/resources/facts.py
trix/resources/feedback.py
trix/resources/graph.py
trix/resources/highlights.py
trix/resources/jobs.py
trix/resources/memories.py
trix/resources/relationships.py
trix/resources/search.py
trix/resources/spaces.py
trix/resources/webhooks.py
trix/testing/__init__.py
trix/testing/mock_client.py
trix/utils/__init__.py
trix/utils/logging.py
trix/utils/metrics.py
trix/utils/pagination.py
trix/utils/retry.py
trix/utils/security.py
trix/utils/telemetry.py
trixdb-0.1.1.dist-info/licenses/LICENSE
trixdb-0.1.1.dist-info/METADATA
trixdb-0.1.1.dist-info/WHEEL
trixdb-0.1.1.dist-info/top_level.txt
trixdb-0.1.1.dist-info/RECORD
