Metadata-Version: 2.4
Name: trixdb
Version: 0.1.1
Summary: Official Python SDK for Trix - Memory and Knowledge Management API
Author-email: Trix Team <support@trixdb.com>
License: MIT
Project-URL: Homepage, https://trixdb.com
Project-URL: Documentation, https://docs.trixdb.com
Project-URL: Repository, https://github.com/trix/trix-python-sdk
Project-URL: Issues, https://github.com/trix/trix-python-sdk/issues
Keywords: trix,memory,knowledge,api,sdk
Classifier: Development Status :: 4 - Beta
Classifier: Intended Audience :: Developers
Classifier: License :: OSI Approved :: MIT License
Classifier: Programming Language :: Python :: 3
Classifier: Programming Language :: Python :: 3.9
Classifier: Programming Language :: Python :: 3.10
Classifier: Programming Language :: Python :: 3.11
Classifier: Programming Language :: Python :: 3.12
Classifier: Typing :: Typed
Requires-Python: >=3.9
License-File: LICENSE
Requires-Dist: httpx>=0.25.0
Requires-Dist: pydantic>=2.0.0
Requires-Dist: typing-extensions>=4.5.0
Provides-Extra: dev
Requires-Dist: pytest>=7.4.0; extra == "dev"
Requires-Dist: pytest-asyncio>=0.21.0; extra == "dev"
Requires-Dist: pytest-cov>=4.1.0; extra == "dev"
Requires-Dist: black>=23.0.0; extra == "dev"
Requires-Dist: ruff>=0.1.0; extra == "dev"
Requires-Dist: mypy>=1.5.0; extra == "dev"
Requires-Dist: respx>=0.20.0; extra == "dev"
Requires-Dist: pip-audit>=2.6.0; extra == "dev"
Provides-Extra: telemetry
Requires-Dist: opentelemetry-api>=1.0.0; extra == "telemetry"
Dynamic: license-file
